cognite/__init__.py
cognite/seismic/__init__.py
cognite/seismic/_api/__init__.py
cognite/seismic/_api/api.py
cognite/seismic/_api/file.py
cognite/seismic/_api/grpc_helpers.py
cognite/seismic/_api/job.py
cognite/seismic/_api/partition.py
cognite/seismic/_api/seismics.py
cognite/seismic/_api/seismicstores.py
cognite/seismic/_api/survey.py
cognite/seismic/_api/traces.py
cognite/seismic/_api/utility.py
cognite/seismic/_api_client.py
cognite/seismic/_interceptors.py
cognite/seismic/_token.py
cognite/seismic/_version.py
cognite/seismic/data_classes/__init__.py
cognite/seismic/data_classes/api_types.py
cognite/seismic/data_classes/errors.py
cognite/seismic/data_classes/extents.py
cognite/seismic/data_classes/geometry.py
cognite/seismic/data_classes/searchspec.py
cognite/seismic/data_classes/trace_data.py
cognite/seismic/protos/__init__.py
cognite/seismic/protos/ingest_job_pb2.py
cognite/seismic/protos/ingest_job_pb2_grpc.py
cognite/seismic/protos/ingest_service_messages_pb2.py
cognite/seismic/protos/ingest_service_messages_pb2_grpc.py
cognite/seismic/protos/ingest_service_pb2.py
cognite/seismic/protos/ingest_service_pb2_grpc.py
cognite/seismic/protos/persisted_trace_pb2.py
cognite/seismic/protos/persisted_trace_pb2_grpc.py
cognite/seismic/protos/query_service_messages_pb2.py
cognite/seismic/protos/query_service_messages_pb2_grpc.py
cognite/seismic/protos/query_service_pb2.py
cognite/seismic/protos/query_service_pb2_grpc.py
cognite/seismic/protos/types_pb2.py
cognite/seismic/protos/types_pb2_grpc.py
cognite/seismic/protos/v1/__init__.py
cognite/seismic/protos/v1/seismic_service_datatypes_pb2.py
cognite/seismic/protos/v1/seismic_service_datatypes_pb2_grpc.py
cognite/seismic/protos/v1/seismic_service_messages_pb2.py
cognite/seismic/protos/v1/seismic_service_messages_pb2_grpc.py
cognite/seismic/protos/v1/seismic_service_pb2.py
cognite/seismic/protos/v1/seismic_service_pb2_grpc.py
cognite_seismic_sdk-0.3.21.dist-info/METADATA
cognite_seismic_sdk-0.3.21.dist-info/WHEEL
cognite_seismic_sdk-0.3.21.dist-info/RECORD
