Metadata-Version: 2.1
Name: cognite-seismic-sdk
Version: 0.3.21
Summary: 
Author: cognite
Author-email: support@cognite.com
Requires-Python: >=3.7,<4.0
Classifier: Programming Language :: Python :: 3
Classifier: Programming Language :: Python :: 3.7
Classifier: Programming Language :: Python :: 3.8
Classifier: Programming Language :: Python :: 3.9
Classifier: Programming Language :: Python :: 3.10
Classifier: Programming Language :: Python :: 3.11
Requires-Dist: deprecation (>=2.1.0,<3.0.0)
Requires-Dist: grpcio (>=1.58,<2.0)
Requires-Dist: grpcio-tools (>=1.58,<2.0)
Requires-Dist: importlib-metadata ; python_version < "3.8"
Requires-Dist: msal (>=1.15.0,<2.0.0)
Requires-Dist: numpy (>=1.21,<2.0)
Requires-Dist: oauthlib (>=3.1.1,<4.0.0)
Requires-Dist: protobuf (>=4.21,<5.0)
Requires-Dist: python-dateutil (>=2.8,<3.0)
Requires-Dist: requests (>=2.26.0,<3.0.0)
Requires-Dist: requests_oauthlib (>=1.3.0,<2.0.0)
Requires-Dist: shapely (>=2.0,<3.0)
Requires-Dist: six (>=1.14,<2.0)
Requires-Dist: urllib3 (>=2.0.0,<3.0.0)
